<?xml version='1.0' encoding='utf-8'?>
<items><item><cae>КА-00036878</cae><name>295/80R22.5    Fulda REGIOCONTROL 3  154/149M HL M+S 3PMSF</name><price>37054</price><rest>2</rest><brand>Fulda</brand><model>REGIOCONTROL 3</model><diameter>22.5</diameter><height>80</height><width>295</width><season>лето</season><img>https://s3.adman.com/img-zapaska/Tires/Fulda/REGIOCONTROL_3.jpg</img><tyretype>Грузовая</tyretype></item><item><cae>00000021032</cae><name>425/85R21    КАМА-1260-2  18PR 156G TT НкШЗ</name><price>62202</price><rest>5</rest><brand>Кама</brand><model>КАМА-1260-2</model><diameter>21</diameter><height>85</height><width>425</width><season>лето</season><img>https://s3.adman.com/img-zapaska/Tires/Кама/КАМА-1260-2.jpg</img><tyretype>Грузовая</tyretype></item><item><cae>КА-00023900</cae><name>10.00R20    YATAI A168 18PR 149/146J TT</name><price>24328</price><rest>10</rest><brand>Yatai</brand><model>A168</model><diameter>20</diameter><width>10.00</width><season>лето</season><img>https://s3.adman.com/img-zapaska/Tires/Yatai/A168.jpg</img><tyretype>Грузовая</tyretype></item><item><cae>КА-00023902</cae><name>11.00R20    YATAI A168  18PR 152/149J TT</name><price>27058</price><rest>3</rest><brand>Yatai</brand><model>A168</model><diameter>20</diameter><width>11.00</width><season>лето</season><img>https://s3.adman.com/img-zapaska/Tires/Yatai/A168.jpg</img><tyretype>Грузовая</tyretype></item><item><cae>КА-00023903</cae><name>11.00R20    YATAI A369  18PR 152/149J TT</name><price>29515</price><rest>8</rest><brand>Yatai</brand><model>A369</model><diameter>20</diameter><width>11.00</width><season>лето</season><img>https://s3.adman.com/img-zapaska/Tires/Yatai/A369.jpg</img><tyretype>Грузовая</tyretype></item><item><cae>КА-00023896</cae><name>11R22.5    YATAI D901  18PR 149/146L TL</name><price>22911</price><rest>2</rest><brand>Yatai</brand><model>D901</model><diameter>22.5</diameter><width>11.00</width><season>лето</season><img>https://s3.adman.com/img-zapaska/Tires/Yatai/D901.jpg</img><tyretype>Грузовая</tyretype></item><item><cae>КА-00023905</cae><name>11R22.5    YATAI T168  16PR 146/143L TL</name><price>20118</price><rest>5</rest><brand>Yatai</brand><model>T168</model><diameter>22.5</diameter><width>11.00</width><season>лето</season><img>https://s3.adman.com/img-zapaska/Tires/Yatai/T168.jpg</img><tyretype>Грузовая</tyretype></item><item><cae>КА-00023907</cae><name>12.00R20    YATAI A168  20PR 156/153K TT</name><price>29400</price><rest>7</rest><brand>Yatai</brand><model>A168</model><diameter>20</diameter><width>12.00</width><season>лето</season><img>https://s3.adman.com/img-zapaska/Tires/Yatai/A168.jpg</img><tyretype>Грузовая</tyretype></item><item><cae>КА-00023908</cae><name>12.00R20    YATAI A369  20PR 156/153J TT</name><price>31773</price><rest>1</rest><brand>Yatai</brand><model>A369</model><diameter>20</diameter><width>12.00</width><season>лето</season><img>https://s3.adman.com/img-zapaska/Tires/Yatai/A369.jpg</img><tyretype>Грузовая</tyretype></item><item><cae>КА-00023928</cae><name>385/65R22.5    YATAI T286  20PR 160K TL</name><price>27510</price><rest>6</rest><brand>Yatai</brand><model>T286</model><diameter>22.5</diameter><height>65</height><width>385</width><season>лето</season><img>https://s3.adman.com/img-zapaska/Tires/Yatai/T286.jpg</img><tyretype>Грузовая</tyretype></item><item><cae>КА-00024305</cae><name>245/70R19.5    КАМА NT202  141/140J TL НкШЗ</name><price>17356</price><rest>2</rest><brand>Кама</brand><model>NT202</model><diameter>19.5</diameter><height>70</height><width>245</width><season>лето</season><img>https://s3.adman.com/img-zapaska/Tires/Кама/NT202.jpg</img><tyretype>Грузовая</tyretype></item><item><cae>КА-00024409</cae><name>215/75R17.5    THREE-A S601 18PR 135/133K TL</name><price>10668</price><rest>1</rest><brand>Three-A</brand><model>S601</model><diameter>17.5</diameter><height>75</height><width>215</width><season>лето</season><img>https://s3.adman.com/img-zapaska/Tires/Three-A/S601.jpg</img><tyretype>Грузовая</tyretype></item><item><cae>КА-00036768</cae><name>245/70R19.5    AMBERSTONE 785  136/134M 16PR TL</name><price>15750</price><rest>9</rest><brand>AMBERSTONE</brand><model>785</model><diameter>19.5</diameter><height>70</height><width>245</width><season>лето</season><img>https://s3.adman.com/img-zapaska/Tires/AMBERSTONE/785.jpg</img><tyretype>Грузовая</tyretype></item><item><cae>КА-00025485</cae><name>295/80R22.5    КАМА NU301   152/150L TL НкШЗ</name><price>25021</price><rest>5</rest><brand>Кама</brand><model>NU301</model><diameter>22.5</diameter><height>80</height><width>295</width><season>лето</season><img>https://s3.adman.com/img-zapaska/Tires/Кама/NU301.jpg</img><tyretype>Грузовая</tyretype></item><item><cae>КА-00026739</cae><name>9.00R20    YATAI A369  16PR  144/142K TT</name><price>22249</price><rest>1</rest><brand>Yatai</brand><model>A369</model><diameter>20</diameter><width>9.00</width><season>лето</season><img>https://s3.adman.com/img-zapaska/Tires/Yatai/A369.jpg</img><tyretype>Грузовая</tyretype></item><item><cae>КА-00036967</cae><name>225/75R17.5    КАМА NR202  129/127M TL НкШЗ</name><price>16569</price><rest>4</rest><brand>Кама</brand><model>NR202</model><diameter>17.5</diameter><height>75</height><width>225</width><season>лето</season><img>https://s3.adman.com/img-zapaska/Tires/Кама/NR202.jpg</img><tyretype>Грузовая</tyretype></item><item><cae>КА-00036872</cae><name>315/80R22.5    Goodyear KMAX S CARGO  156L/154M M+S</name><price>44289</price><rest>4</rest><brand>Goodyear</brand><model>KMAX S CARGO</model><diameter>22.5</diameter><height>80</height><width>315</width><season>лето</season><img>https://s3.adman.com/img-zapaska/Tires/Goodyear/KMAX_S_CARGO.jpg</img><tyretype>Грузовая</tyretype></item><item><cae>КА-00039107</cae><name>11R22.5    THREE-A T168 18PR 149/146L TL</name><price>21241</price><rest>3</rest><brand>Three-A</brand><model>T168</model><diameter>22.5</diameter><width>11.00</width><season>лето</season><img>https://s3.adman.com/img-zapaska/Tires/Three-A/T168.jpg</img><tyretype>Грузовая</tyretype></item><item><cae>КА-00041093</cae><name>315/80R22.5    YATAI T168 20PR 156/153K TL</name><price>24097</price><rest>12</rest><brand>Yatai</brand><model>T168</model><diameter>22.5</diameter><height>80</height><width>315</width><season>лето</season><img>https://s3.adman.com/img-zapaska/Tires/Yatai/T168.jpg</img><tyretype>Грузовая</tyretype></item><item><cae>КА-00036881</cae><name>315/80R22.5    Fulda REGIOCONTROL 3  156L/154M M+S 3PMSF</name><price>35721</price><rest>6</rest><brand>Fulda</brand><model>REGIOCONTROL 3</model><diameter>22.5</diameter><height>80</height><width>315</width><season>лето</season><img>https://s3.adman.com/img-zapaska/Tires/Fulda/REGIOCONTROL_3.jpg</img><tyretype>Грузовая</tyretype></item><item><cae>00000011596</cae><name>9.00R20    О-40БМ  14PR 140/137J TT НкШЗ</name><price>17125</price><rest>10</rest><brand>Кама</brand><model>О-40БМ</model><diameter>20</diameter><width>9.00</width><season>лето</season><img>https://s3.adman.com/img-zapaska/Tires/Кама/О-40БМ.jpg</img><tyretype>Грузовая</tyretype></item><item><cae>КА-00036722</cae><name>7.50R16LT    AMBERSTONE 386  124/120K 16PR TT</name><price>12222</price><rest>7</rest><brand>AMBERSTONE</brand><model>386</model><diameter>16</diameter><width>7.50</width><season>лето</season><img>https://s3.adman.com/img-zapaska/Tires/AMBERSTONE/386.jpg</img><tyretype>Грузовая</tyretype></item><item><cae>00000020022</cae><name>295/75R22.5    КАМА NR202  148/145M TL НкШЗ</name><price>27121</price><rest>4</rest><brand>Кама</brand><model>NR202</model><diameter>22.5</diameter><height>75</height><width>295</width><season>лето</season><img>https://s3.adman.com/img-zapaska/Tires/Кама/NR202.jpg</img><tyretype>Грузовая</tyretype></item><item><cae>КА-00036769</cae><name>265/70R19.5    AMBERSTONE 785  140/138M 16PR TL</name><price>16621</price><rest>17</rest><brand>AMBERSTONE</brand><model>785</model><diameter>19.5</diameter><height>70</height><width>265</width><season>лето</season><img>https://s3.adman.com/img-zapaska/Tires/AMBERSTONE/785.jpg</img><tyretype>Грузовая</tyretype></item><item><cae>КА-00037609</cae><name>385/65R22.5    MAXXIS MS290 20PR  160K TL</name><price>37579</price><rest>1</rest><brand>MAXXIS</brand><model>MS290</model><diameter>22.5</diameter><height>65</height><width>285</width><season>лето</season><img>https://s3.adman.com/img-zapaska/Tires/MAXXIS/MS290.jpg</img><tyretype>Грузовая</tyretype></item><item><cae>КА-00036776</cae><name>315/70R22.5    AMBERSTONE 785  156/150L 18PR TL</name><price>25126</price><rest>21</rest><brand>AMBERSTONE</brand><model>785</model><diameter>22.5</diameter><height>70</height><width>315</width><season>лето</season><img>https://s3.adman.com/img-zapaska/Tires/AMBERSTONE/785.jpg</img><tyretype>Грузовая</tyretype></item><item><cae>КА-00036654</cae><name>6.50R16LT    AMBERSTONE 300  110/105L 12PR TT</name><price>7822</price><rest>16</rest><brand>AMBERSTONE</brand><model>300</model><diameter>16</diameter><width>6.50</width><season>лето</season><img>https://s3.adman.com/img-zapaska/Tires/AMBERSTONE/300.jpg</img><tyretype>Грузовая</tyretype></item><item><cae>КА-00036679</cae><name>10.00R20    AMBERSTONE 308  149/146K 18PR TT</name><price>25095</price><rest>12</rest><brand>AMBERSTONE</brand><model>308</model><diameter>20</diameter><width>10.00</width><season>лето</season><img>https://s3.adman.com/img-zapaska/Tires/AMBERSTONE/308.jpg</img><tyretype>Грузовая</tyretype></item><item><cae>КА-00036870</cae><name>315/70R22.5    Goodyear REGIONAL RHS II  154L/152M</name><price>44982</price><rest>1</rest><brand>Goodyear</brand><model>REGIONAL RHS II</model><diameter>22.5</diameter><height>70</height><width>315</width><season>лето</season><img>https://s3.adman.com/img-zapaska/Tires/Goodyear/REGIONAL_RHS_II.jpg</img><tyretype>Грузовая</tyretype></item><item><cae>КА-00036757</cae><name>315/80R22.5    AMBERSTONE 755  157/154M 20PR TL</name><price>24622</price><rest>34</rest><brand>AMBERSTONE</brand><model>755</model><diameter>22.5</diameter><height>80</height><width>315</width><season>лето</season><img>https://s3.adman.com/img-zapaska/Tires/AMBERSTONE/755.jpg</img><tyretype>Грузовая</tyretype></item><item><cae>КА-00036697</cae><name>235/75R17.5    AMBERSTONE 366  143/141J 18PR TL</name><price>13282</price><rest>34</rest><brand>AMBERSTONE</brand><model>366</model><diameter>17.5</diameter><height>75</height><width>235</width><season>лето</season><img>https://s3.adman.com/img-zapaska/Tires/AMBERSTONE/366.jpg</img><tyretype>Грузовая</tyretype></item><item><cae>00000004129</cae><name>12.00R20              Kormoran D  154/150K</name><price>18270</price><rest>1</rest><brand>Kormoran</brand><model>D</model><diameter>20</diameter><width>12.00</width><season>лето</season><img>https://s3.adman.com/img-zapaska/Tires/Kormoran/D.jpg</img><tyretype>Грузовая</tyretype></item><item><cae>КА-00045626</cae><name>12.00 R18    NORTEC TR-115  135K TT</name><price>30943</price><rest>2</rest><brand>NORTEC</brand><model>TR-115</model><diameter>18</diameter><width>12.00</width><season>лето</season><img>https://s3.adman.com/img-zapaska/Tires/NORTEC/TR-115.jpg</img><tyretype>Грузовая</tyretype></item><item><cae>КА-00049549</cae><name>295/80R22.5    КАМА NR501  152/148M TL НкШЗ</name><price>26481</price><rest>3</rest><brand>Кама</brand><model>NR501</model><diameter>22.5</diameter><height>80</height><width>295</width><season>зима</season><img>https://s3.adman.com/img-zapaska/Tires/Кама/NR501.jpg</img><tyretype>Грузовая</tyretype></item><item><cae>КА-00052404</cae><name>245/70R17.5    КАМА NR202  136/134M TL НкШЗ</name><price>16695</price><rest>4</rest><brand>Кама</brand><model>NR202</model><diameter>17.5</diameter><height>70</height><width>245</width><season>лето</season><img>https://s3.adman.com/img-zapaska/Tires/Кама/NR202.jpg</img><tyretype>Грузовая</tyretype></item><item><cae>КА-00027909</cae><name>10.00R20    КАМА NU903  149/146K TТ НкШЗ</name><price>23383</price><rest>14</rest><brand>Кама</brand><model>NU903</model><diameter>20</diameter><width>10.00</width><season>лето</season><img>https://s3.adman.com/img-zapaska/Tires/Кама/NU903.jpg</img><tyretype>Грузовая</tyretype></item><item><cae>КА-00028338</cae><name>9.00R20    YATAI A168  16PR  144/142K TT</name><price>21042</price><rest>1</rest><brand>Yatai</brand><model>A168</model><diameter>20</diameter><width>9.00</width><season>лето</season><img>https://s3.adman.com/img-zapaska/Tires/Yatai/A168.jpg</img><tyretype>Грузовая</tyretype></item><item><cae>00000028310</cae><name>315/60R22.5    CORDIANT PROFESSIONAL DL-1 152/148L TL  ЯШЗ</name><price>31426</price><rest>4</rest><brand>Cordiant</brand><model>DL-1</model><diameter>22.5</diameter><height>60</height><width>315</width><season>лето</season><img>https://s3.adman.com/img-zapaska/Tires/Cordiant/DL-1.jpg</img><tyretype>Грузовая</tyretype></item><item><cae>КА-00008427</cae><name>385/65R22.5    КАМА NF202  160K TL НкШЗ</name><price>32959</price><rest>8</rest><brand>Кама</brand><model>NF202</model><diameter>22.5</diameter><height>65</height><width>385</width><season>лето</season><img>https://s3.adman.com/img-zapaska/Tires/Кама/NF202.jpg</img><tyretype>Грузовая</tyretype></item><item><cae>КА-00008426</cae><name>425/85R21    КАМА-1260-2  14PR 146J TT НкШЗ</name><price>59272</price><rest>4</rest><brand>Кама</brand><model>КАМА-1260-2</model><diameter>21</diameter><height>85</height><width>425</width><season>лето</season><img>https://s3.adman.com/img-zapaska/Tires/Кама/КАМА-1260-2.jpg</img><tyretype>Грузовая</tyretype></item><item><cae>КА-00036773</cae><name>295/80R22.5    AMBERSTONE 785  154/151M 18PR TL</name><price>24265</price><rest>10</rest><brand>AMBERSTONE</brand><model>785</model><diameter>22.5</diameter><height>80</height><width>295</width><season>лето</season><img>https://s3.adman.com/img-zapaska/Tires/AMBERSTONE/785.jpg</img><tyretype>Грузовая</tyretype></item><item><cae>КА-00036727</cae><name>11.00R20    AMBERSTONE 386  152/149K 18PR TT</name><price>30597</price><rest>12</rest><brand>AMBERSTONE</brand><model>386</model><diameter>20</diameter><width>11.00</width><season>лето</season><img>https://s3.adman.com/img-zapaska/Tires/AMBERSTONE/386.jpg</img><tyretype>Грузовая</tyretype></item><item><cae>КА-00036885</cae><name>275/70R22.5    Sava CITY U4  148J/152E M+S 3PMSF</name><price>32434</price><rest>1</rest><brand>Sava</brand><model>CITY U4</model><diameter>22.5</diameter><height>70</height><width>275</width><season>лето</season><img>https://s3.adman.com/img-zapaska/Tires/Sava/CITY_U4.jpg</img><tyretype>Грузовая</tyretype></item><item><cae>КА-00036886</cae><name>315/70R22.5    Sava ORJAK 5  154L/152M M+S 3PMSF</name><price>39217</price><rest>3</rest><brand>Sava</brand><model>ORJAK 5</model><diameter>22.5</diameter><height>70</height><width>315</width><season>лето</season><img>https://s3.adman.com/img-zapaska/Tires/Sava/ORJAK_5.jpg</img><tyretype>Грузовая</tyretype></item><item><cae>КА-00037607</cae><name>315/80R22.5    MAXXIS MA219 18PR  154/150M TL</name><price>34293</price><rest>4</rest><brand>MAXXIS</brand><model>MA219</model><diameter>22.5</diameter><height>80</height><width>315</width><season>лето</season><img>https://s3.adman.com/img-zapaska/Tires/MAXXIS/MA219.jpg</img><tyretype>Грузовая</tyretype></item><item><cae>КА-00036657</cae><name>8.25R16LT    AMBERSTONE 300  128/124M 16PR TT</name><price>12568</price><rest>20</rest><brand>AMBERSTONE</brand><model>300</model><diameter>16</diameter><width>8.25</width><season>лето</season><img>https://s3.adman.com/img-zapaska/Tires/AMBERSTONE/300.jpg</img><tyretype>Грузовая</tyretype></item><item><cae>КА-00056581</cae><name>215/75R17.5    COMPASAL CPT76  135/133J 18PR TL</name><price>10899</price><rest>11</rest><brand>Compasal</brand><model>CPT76</model><diameter>17.5</diameter><height>75</height><width>215</width><season>лето</season><img>https://s3.adman.com/img-zapaska/Tires/Compasal/CPT76.jpg</img><tyretype>Грузовая</tyretype></item><item><cae>КА-00036873</cae><name>315/80R22.5    Goodyear KMAX D CARGO  156L/154M M+S 3PMSF</name><price>44583</price><rest>16</rest><brand>Goodyear</brand><model>KMAX D CARGO</model><diameter>22.5</diameter><height>80</height><width>315</width><season>лето</season><img>https://s3.adman.com/img-zapaska/Tires/Goodyear/KMAX_D_CARGO.jpg</img><tyretype>Грузовая</tyretype></item><item><cae>КА-00037556</cae><name>11R22.5    MAXXIS UR288 16PR  148/145L TL</name><price>28560</price><rest>14</rest><brand>MAXXIS</brand><model>UR288</model><diameter>22.5</diameter><width>11.00</width><season>лето</season><img>https://s3.adman.com/img-zapaska/Tires/MAXXIS/UR288.jpg</img><tyretype>Грузовая</tyretype></item><item><cae>00000004956</cae><name>425/85R21    TYREX CRG POWER О-184  18PR 156J TT  ОШЗ</name><price>60427</price><rest>2</rest><brand>Tyrex</brand><model>О-184</model><diameter>21</diameter><height>85</height><width>425</width><season>лето</season><img>https://s3.adman.com/img-zapaska/Tires/Tyrex/О-184.jpg</img><tyretype>Грузовая</tyretype></item><item><cae>00000015863</cae><name>385/65R22.5    CORDIANT PROFESSIONAL TR-1 160K(158L) TL  ЯШЗ</name><price>36393</price><rest>10</rest><brand>Cordiant</brand><model>TR-1</model><diameter>22.5</diameter><height>65</height><width>385</width><season>лето</season><img>https://s3.adman.com/img-zapaska/Tires/Cordiant/TR-1.jpg</img><tyretype>Грузовая</tyretype></item><item><cae>00000007979</cae><name>275/70R22.5    КАМА NF201  148/145M TL НкШЗ</name><price>23845</price><rest>1</rest><brand>Кама</brand><model>NF201</model><diameter>22.5</diameter><height>70</height><width>275</width><season>лето</season><img>https://s3.adman.com/img-zapaska/Tires/Кама/NF201.jpg</img><tyretype>Грузовая</tyretype></item><item><cae>КА-00023919</cae><name>295/80R22.5    YATAI T176  18PR 152/149M TL</name><price>21441</price><rest>1</rest><brand>Yatai</brand><model>T176</model><diameter>22.5</diameter><height>80</height><width>295</width><season>лето</season><img>https://s3.adman.com/img-zapaska/Tires/Yatai/T176.jpg</img><tyretype>Грузовая</tyretype></item><item><cae>КА-00024628</cae><name>295/80R22.5    THREE-A T298 18PR 152/149J TL</name><price>22774</price><rest>7</rest><brand>Three-A</brand><model>T298</model><diameter>22.5</diameter><height>80</height><width>295</width><season>лето</season><img>https://s3.adman.com/img-zapaska/Tires/Three-A/T298.jpg</img><tyretype>Грузовая</tyretype></item><item><cae>КА-00056526</cae><name>315/70R22.5    COMPASAL CPS21  154/150M 20PR TL</name><price>24612</price><rest>14</rest><brand>Compasal</brand><model>CPS21</model><diameter>22.5</diameter><height>70</height><width>315</width><season>лето</season><img>https://s3.adman.com/img-zapaska/Tires/Compasal/CPS21.jpg</img><tyretype>Грузовая</tyretype></item><item><cae>00000017128</cae><name>235/75R17.5    КАМА NR202  132/130M TL НкШЗ</name><price>15435</price><rest>4</rest><brand>Кама</brand><model>NR202</model><diameter>17.5</diameter><height>75</height><width>235</width><season>лето</season><img>https://s3.adman.com/img-zapaska/Tires/Кама/NR202.jpg</img><tyretype>Грузовая</tyretype></item><item><cae>КА-00008544</cae><name>425/85R21    TYREX CRG POWER VO-1260  20PR 160J TT  ОШЗ</name><price>63777</price><rest>2</rest><brand>Tyrex</brand><model>VO-1260</model><diameter>21</diameter><height>85</height><width>425</width><season>лето</season><img>https://s3.adman.com/img-zapaska/Tires/Tyrex/VO-1260.jpg</img><tyretype>Грузовая</tyretype></item><item><cae>КА-00036708</cae><name>295/80R22.5    AMBERSTONE 366  154/151M 18PR TL</name><price>22932</price><rest>4</rest><brand>AMBERSTONE</brand><model>366</model><diameter>22.5</diameter><height>80</height><width>295</width><season>лето</season><img>https://s3.adman.com/img-zapaska/Tires/AMBERSTONE/366.jpg</img><tyretype>Грузовая</tyretype></item><item><cae>КА-00056509</cae><name>215/75R17.5    COMPASAL CPS21  135/133J 18PR TL</name><price>11014</price><rest>4</rest><brand>Compasal</brand><model>CPS21</model><diameter>17.5</diameter><height>75</height><width>215</width><season>лето</season><img>https://s3.adman.com/img-zapaska/Tires/Compasal/CPS21.jpg</img><tyretype>Грузовая</tyretype></item><item><cae>КА-00044899</cae><name>235/75R17.5    THREE-A D901  18PR 143/141K TL</name><price>13366</price><rest>5</rest><brand>Three-A</brand><model>D901</model><diameter>17.5</diameter><height>75</height><width>235</width><season>лето</season><img>https://s3.adman.com/img-zapaska/Tires/Three-A/D901.jpg</img><tyretype>Грузовая</tyretype></item><item><cae>КА-00056619</cae><name>10R22.5    AMBERSTONE 366  144/142M 16PR TL</name><price>21010</price><rest>12</rest><brand>AMBERSTONE</brand><model>366</model><diameter>22.5</diameter><width>10.00</width><season>лето</season><img>https://s3.adman.com/img-zapaska/Tires/AMBERSTONE/366.jpg</img><tyretype>Грузовая</tyretype></item><item><cae>КА-00037881</cae><name>315/80R22.5    BFGoodrich ROUTE CONTROL S  156/150L TL</name><price>34093</price><rest>10</rest><brand>BFGoodrich</brand><model>ROUTE CONTROL S</model><diameter>22.5</diameter><height>80</height><width>315</width><season>лето</season><img>https://s3.adman.com/img-zapaska/Tires/BFGoodrich/ROUTE_CONTROL_S.jpg</img><tyretype>Грузовая</tyretype></item><item><cae>КА-00037584</cae><name>385/65R22.5    MAXXIS MA299 20PR  160K/15L TL</name><price>34996</price><rest>&gt;40</rest><brand>MAXXIS</brand><model>MA299</model><diameter>22.5</diameter><height>65</height><width>385</width><season>лето</season><img>https://s3.adman.com/img-zapaska/Tires/MAXXIS/MA299.jpg</img><tyretype>Грузовая</tyretype></item><item><cae>00000016916</cae><name>215/75R17.5    КАМА NF202  126/124M TL НкШЗ</name><price>13377</price><rest>1</rest><brand>Кама</brand><model>NF202</model><diameter>17.5</diameter><height>75</height><width>215</width><season>лето</season><img>https://s3.adman.com/img-zapaska/Tires/Кама/NF202.jpg</img><tyretype>Грузовая</tyretype></item><item><cae>КА-00036740</cae><name>385/65R22.5    AMBERSTONE 397  160K 20PR TL</name><price>29179</price><rest>10</rest><brand>AMBERSTONE</brand><model>397</model><diameter>22.5</diameter><height>65</height><width>385</width><season>лето</season><img>https://s3.adman.com/img-zapaska/Tires/AMBERSTONE/397.jpg</img><tyretype>Грузовая</tyretype></item><item><cae>00000028960</cae><name>385/55R22.5    КАМА NT202+  160K TL НкШЗ</name><price>33495</price><rest>4</rest><brand>Кама</brand><model>NT202+</model><diameter>22.5</diameter><height>55</height><width>385</width><season>лето</season><img>https://s3.adman.com/img-zapaska/Tires/Кама/NT202_.jpg</img><tyretype>Грузовая</tyretype></item><item><cae>00000029211</cae><name>10.00R20    TYREX CRG VM-310  18PR 149/146K TT  ОШЗ</name><price>19351</price><rest>6</rest><brand>Tyrex</brand><model>VM-310</model><diameter>20</diameter><width>10.00</width><season>лето</season><img>https://s3.adman.com/img-zapaska/Tires/Tyrex/VM-310.jpg</img><tyretype>Грузовая</tyretype></item><item><cae>КА-00056514</cae><name>245/70R19.5    COMPASAL CPS21  143/141J 18PR TL</name><price>15351</price><rest>12</rest><brand>Compasal</brand><model>CPS21</model><diameter>19.5</diameter><height>70</height><width>245</width><season>лето</season><img>https://s3.adman.com/img-zapaska/Tires/Compasal/CPS21.jpg</img><tyretype>Грузовая</tyretype></item><item><cae>00000005053</cae><name>12.00R20    TYREX CRG VM-201  18PR 154/149J TT  ОШЗ</name><price>23509</price><rest>8</rest><brand>Tyrex</brand><model>VM-201</model><diameter>20</diameter><width>12.00</width><season>лето</season><img>https://s3.adman.com/img-zapaska/Tires/Tyrex/VM-201_.jpg</img><tyretype>Грузовая</tyretype></item><item><cae>КА-00021639</cae><name>295/75R22.5    КАМА NF202  148/145M TL НкШЗ</name><price>26155</price><rest>2</rest><brand>Кама</brand><model>NF202</model><diameter>22.5</diameter><height>75</height><width>295</width><season>лето</season><img>https://s3.adman.com/img-zapaska/Tires/Кама/NF202.jpg</img><tyretype>Грузовая</tyretype></item><item><cae>КА-00036888</cae><name>315/80R22.5    Sava ORJAK 5  154L/152M M+S 3PMSF</name><price>35721</price><rest>16</rest><brand>Sava</brand><model>ORJAK 5</model><diameter>22.5</diameter><height>80</height><width>315</width><season>лето</season><img>https://s3.adman.com/img-zapaska/Tires/Sava/ORJAK_5.jpg</img><tyretype>Грузовая</tyretype></item><item><cae>КА-00036875</cae><name>315/80R22.5    Goodyear OMNITRAC D HD  156/150K M+S 3PMSF</name><price>38104</price><rest>3</rest><brand>Goodyear</brand><model>OMNITRAC D HD</model><diameter>22.5</diameter><height>80</height><width>315</width><season>лето</season><img>https://s3.adman.com/img-zapaska/Tires/Goodyear/OMNITRAC_D_HD.jpg</img><tyretype>Грузовая</tyretype></item><item><cae>КА-00036659</cae><name>11R22.5    AMBERSTONE 300  146/143M 16PR TL</name><price>21441</price><rest>21</rest><brand>AMBERSTONE</brand><model>300</model><diameter>22.5</diameter><width>11.00</width><season>лето</season><img>https://s3.adman.com/img-zapaska/Tires/AMBERSTONE/300.jpg</img><tyretype>Грузовая</tyretype></item><item><cae>КА-00056559</cae><name>7.50R16    COMPASAL CPS60  122/118L 14PR TT</name><price>10794</price><rest>6</rest><brand>Compasal</brand><model>CPS60</model><diameter>16</diameter><width>7.50</width><season>лето</season><img>https://s3.adman.com/img-zapaska/Tires/Compasal/CPS60.jpg</img><tyretype>Грузовая</tyretype></item><item><cae>КА-00036663</cae><name>10.00R20    AMBERSTONE 300  149/146L 18PR TT</name><price>25095</price><rest>16</rest><brand>AMBERSTONE</brand><model>300</model><diameter>20</diameter><width>10.00</width><season>лето</season><img>https://s3.adman.com/img-zapaska/Tires/AMBERSTONE/300.jpg</img><tyretype>Грузовая</tyretype></item><item><cae>00000026848</cae><name>315/60R22.5    CORDIANT PROFESSIONAL FL-1 152/148L TL  ЯШЗ</name><price>30513</price><rest>2</rest><brand>Cordiant</brand><model>FL-1</model><diameter>22.5</diameter><height>60</height><width>315</width><season>лето</season><img>https://s3.adman.com/img-zapaska/Tires/Cordiant/FL-1.jpg</img><tyretype>Грузовая</tyretype></item><item><cae>КА-00036709</cae><name>315/70R22.5    AMBERSTONE 366  156/150L 18PR TL</name><price>22995</price><rest>12</rest><brand>AMBERSTONE</brand><model>366</model><diameter>22.5</diameter><height>70</height><width>315</width><season>лето</season><img>https://s3.adman.com/img-zapaska/Tires/AMBERSTONE/366.jpg</img><tyretype>Грузовая</tyretype></item><item><cae>КА-00056476</cae><name>315/70R22.5    COMPASAL CPD81  154/150M 20PR TL</name><price>25819</price><rest>7</rest><brand>Compasal</brand><model>CPD81</model><diameter>22.5</diameter><height>70</height><width>315</width><season>лето</season><img>https://s3.adman.com/img-zapaska/Tires/Compasal/CPD81.jpg</img><tyretype>Грузовая</tyretype></item><item><cae>КА-00036887</cae><name>315/80R22.5    Sava AVANT 5  156/150L M+S 3PMSF</name><price>34923</price><rest>23</rest><brand>Sava</brand><model>AVANT 5</model><diameter>22.5</diameter><height>80</height><width>315</width><season>лето</season><img>https://s3.adman.com/img-zapaska/Tires/Sava/AVANT_5.jpg</img><tyretype>Грузовая</tyretype></item><item><cae>КА-00036869</cae><name>295/80R22.5    Goodyear OMNİTRAC D  152/148K M+S 3PMSF</name><price>39889</price><rest>4</rest><brand>Goodyear</brand><model>OMNİTRAC D</model><diameter>22.5</diameter><height>80</height><width>295</width><season>лето</season><img>https://s3.adman.com/img-zapaska/Tires/Goodyear/OMNİTRAC_D.jpg</img><tyretype>Грузовая</tyretype></item><item><cae>00000017734</cae><name>215/75R17.5    КАМА NU301  126/124M TL НкШЗ</name><price>13503</price><rest>4</rest><brand>Кама</brand><model>NU301</model><diameter>17.5</diameter><height>75</height><width>215</width><season>лето</season><img>https://s3.adman.com/img-zapaska/Tires/Кама/NU301.jpg</img><tyretype>Грузовая</tyretype></item><item><cae>КА-00056458</cae><name>11.00R20    COMPASAL CPD68+  152/149K 18PR TT</name><price>28591</price><rest>4</rest><brand>Compasal</brand><model>CPD68+</model><diameter>20</diameter><width>11.00</width><season>лето</season><img>https://s3.adman.com/img-zapaska/Tires/Compasal/CPD68+.jpg</img><tyretype>Грузовая</tyretype></item><item><cae>КА-00036725</cae><name>9.00R20    AMBERSTONE 386  144/142K 16PR TT</name><price>24087</price><rest>19</rest><brand>AMBERSTONE</brand><model>386</model><diameter>20</diameter><width>9.00</width><season>лето</season><img>https://s3.adman.com/img-zapaska/Tires/AMBERSTONE/386.jpg</img><tyretype>Грузовая</tyretype></item><item><cae>КА-00036660</cae><name>9.00R20    AMBERSTONE 300  144/142L 16PR TT</name><price>21945</price><rest>36</rest><brand>AMBERSTONE</brand><model>300</model><diameter>20</diameter><width>9.00</width><season>лето</season><img>https://s3.adman.com/img-zapaska/Tires/AMBERSTONE/300.jpg</img><tyretype>Грузовая</tyretype></item><item><cae>КА-00063770</cae><name>295/80R22.5    КАМА FORZA REG S   152/148K TL НкШЗ</name><price>23247</price><rest>2</rest><brand>Кама</brand><model>REG D</model><diameter>22.5</diameter><height>80</height><width>295</width><season>лето</season><img>https://s3.adman.com/img-zapaska/Tires/Кама/REG_D.jpg</img><tyretype>Грузовая</tyretype></item><item><cae>КА-00063771</cae><name>315/80R22.5    КАМА FORZA REG D  154/150K TL НкШЗ</name><price>25977</price><rest>4</rest><brand>Кама</brand><model>FORZA</model><diameter>22.5</diameter><height>80</height><width>315</width><season>лето</season><img>https://s3.adman.com/img-zapaska/Tires/Кама/FORZA.jpg</img><tyretype>Грузовая</tyretype></item><item><cae>00000012134</cae><name>9.00R20    О-40БМ-1  14PR 140/137J TT  ОШЗ</name><price>16642</price><rest>8</rest><brand>ОШЗ</brand><model>О-40БМ</model><diameter>20</diameter><width>9.00</width><season>лето</season><img>https://s3.adman.com/img-zapaska/Tires/ОШЗ/О-40БМ.jpg</img><tyretype>Грузовая</tyretype></item><item><cae>КА-00036748</cae><name>295/75R22.5    AMBERSTONE 660  146/143L 16PR TL</name><price>23257</price><rest>10</rest><brand>AMBERSTONE</brand><model>660</model><diameter>22.5</diameter><height>75</height><width>295</width><season>лето</season><tyretype>Грузовая</tyretype></item><item><cae>00000024419</cae><name>385/65R22.5    КАМА NT202  160K TL НкШЗ</name><price>29452</price><rest>9</rest><brand>Кама</brand><model>NT202</model><diameter>22.5</diameter><height>65</height><width>385</width><season>лето</season><img>https://s3.adman.com/img-zapaska/Tires/Кама/NT202.jpg</img><tyretype>Грузовая</tyretype></item><item><cae>00000025802</cae><name>10.00R20    TYREX CRG VM-310  16PR 146/143K TT  ОШЗ</name><price>18480</price><rest>8</rest><brand>Tyrex</brand><model>VM-310</model><diameter>20</diameter><width>10.00</width><season>лето</season><img>https://s3.adman.com/img-zapaska/Tires/Tyrex/VM-310.jpg</img><tyretype>Грузовая</tyretype></item><item><cae>00000025806</cae><name>8.25R20    У-2  14PR 133/131K TT  ОШЗ</name><price>13513</price><rest>16</rest><brand>ОШЗ</brand><model>У-2</model><diameter>20</diameter><width>8.25</width><season>лето</season><img>https://s3.adman.com/img-zapaska/Tires/ОШЗ/У-2.jpg</img><tyretype>Грузовая</tyretype></item><item><cae>00000025919</cae><name>315/80R22.5    TYREX ALL STEEL DR-1 154/150M TL  ЯШЗ</name><price>24202</price><rest>3</rest><brand>Tyrex</brand><model>DR-1</model><diameter>22.5</diameter><height>80</height><width>315</width><season>лето</season><img>https://s3.adman.com/img-zapaska/Tires/Tyrex/DR-1.jpg</img><tyretype>Грузовая</tyretype></item><item><cae>00000025922</cae><name>295/80R22.5    TYREX ALL STEEL DR-1 152/148M TL  ЯШЗ</name><price>24685</price><rest>4</rest><brand>Tyrex</brand><model>DR-1</model><diameter>22.5</diameter><height>80</height><width>295</width><season>лето</season><img>https://s3.adman.com/img-zapaska/Tires/Tyrex/DR-1.jpg</img><tyretype>Грузовая</tyretype></item><item><cae>КА-00036703</cae><name>265/70R19.5    AMBERSTONE 366  143/141J 18PR TL</name><price>16621</price><rest>14</rest><brand>AMBERSTONE</brand><model>366</model><diameter>19.5</diameter><height>70</height><width>265</width><season>лето</season><img>https://s3.adman.com/img-zapaska/Tires/AMBERSTONE/366.jpg</img><tyretype>Грузовая</tyretype></item><item><cae>КА-00037555</cae><name>295/80R22.5    MAXXIS UR279 16PR  152/148M TL</name><price>33988</price><rest>1</rest><brand>MAXXIS</brand><model>UR279</model><diameter>22.5</diameter><height>80</height><width>295</width><season>лето</season><img>https://s3.adman.com/img-zapaska/Tires/MAXXIS/UR279.jpg</img><tyretype>Грузовая</tyretype></item><item><cae>КА-00041760</cae><name>11.00R20    THREE-A  A168  18PR 152/149J TT</name><price>27058</price><rest>14</rest><brand>Three-A</brand><model>A168</model><diameter>20</diameter><width>11.00</width><season>лето</season><img>https://s3.adman.com/img-zapaska/Tires/Three-A/A168.jpg</img><tyretype>Грузовая</tyretype></item><item><cae>КА-00035709</cae><name>295/80R22.5  Белшина BEL-246  152/149M TL</name><price>25588</price><rest>1</rest><brand>Белшина</brand><model>BEL-246</model><diameter>22.5</diameter><height>80</height><width>295</width><season>лето</season><img>https://s3.adman.com/img-zapaska/Tires/Белшина/BEL-246.jpg</img><tyretype>Грузовая</tyretype></item><item><cae>00000017522</cae><name>315/80R22.5    КАМА NR201  156/150L TL НкШЗ</name><price>28119</price><rest>7</rest><brand>Кама</brand><model>NR201</model><diameter>22.5</diameter><height>80</height><width>315</width><season>лето</season><img>https://s3.adman.com/img-zapaska/Tires/Кама/NR201.jpg</img><tyretype>Грузовая</tyretype></item><item><cae>КА-00036877</cae><name>385/65R22.5    Goodyear OMNITRAC MST II HCT  160K/158L M+S</name><price>43732</price><rest>16</rest><brand>Goodyear</brand><model>OMNITRAC MST II HCT</model><diameter>22.5</diameter><height>65</height><width>385</width><season>лето</season><img>https://s3.adman.com/img-zapaska/Tires/Goodyear/OMNITRAC_MST_II_HCT.jpg</img><tyretype>Грузовая</tyretype></item><item><cae>КА-00036671</cae><name>11.00R20    AMBERSTONE 302  152/149L 18PR TT</name><price>30198</price><rest>10</rest><brand>AMBERSTONE</brand><model>302</model><diameter>20</diameter><width>11.00</width><season>лето</season><img>https://s3.adman.com/img-zapaska/Tires/AMBERSTONE/302.jpg</img><tyretype>Грузовая</tyretype></item><item><cae>КА-00036739</cae><name>385/65R22.5    AMBERSTONE 396  160K 20PR TL</name><price>29179</price><rest>26</rest><brand>AMBERSTONE</brand><model>396</model><diameter>22.5</diameter><height>65</height><width>385</width><season>лето</season><img>https://s3.adman.com/img-zapaska/Tires/AMBERSTONE/396.jpg</img><tyretype>Грузовая</tyretype></item><item><cae>00000015860</cae><name>295/80R22.5    CORDIANT PROFESSIONAL DR-1 152/148M TL  ЯШЗ</name><price>32833</price><rest>9</rest><brand>Cordiant</brand><model>DR-1</model><diameter>22.5</diameter><height>80</height><width>295</width><season>лето</season><img>https://s3.adman.com/img-zapaska/Tires/Cordiant/DR-1.jpg</img><tyretype>Грузовая</tyretype></item><item><cae>КА-00056558</cae><name>315/80R22.5    COMPASAL CPS60  156/150M 20PR TL</name><price>23373</price><rest>8</rest><brand>Compasal</brand><model>CPS60</model><diameter>22.5</diameter><height>80</height><width>315</width><season>лето</season><img>https://s3.adman.com/img-zapaska/Tires/Compasal/CPS60.jpg</img><tyretype>Грузовая</tyretype></item><item><cae>КА-00035704</cae><name>235/75R17.5  Белшина BEL-159  130/128M TL</name><price>15393</price><rest>7</rest><brand>Белшина</brand><model>BEL-159</model><diameter>17.5</diameter><height>75</height><width>235</width><season>лето</season><img>https://s3.adman.com/img-zapaska/Tires/Белшина/BEL-159.jpg</img><tyretype>Грузовая</tyretype></item><item><cae>КА-00036892</cae><name>385/65R22.5    Kelly ARMORSTEEL KTR2  164K HL M+S 3PMSF</name><price>38199</price><rest>12</rest><brand>Kelly</brand><model>ARMORSTEEL KTR2</model><diameter>22.5</diameter><height>65</height><width>385</width><season>лето</season><img>https://s3.adman.com/img-zapaska/Tires/Kelly/ARMORSTEEL_KTR2.jpg</img><tyretype>Грузовая</tyretype></item><item><cae>КА-00056589</cae><name>385/65R22.5    COMPASAL CPT76  160L 20PR TL</name><price>28612</price><rest>18</rest><brand>Compasal</brand><model>CPT76</model><diameter>22.5</diameter><height>65</height><width>385</width><season>лето</season><img>https://s3.adman.com/img-zapaska/Tires/Compasal/CPT76.jpg</img><tyretype>Грузовая</tyretype></item><item><cae>КА-00037582</cae><name>11R22.5    MAXXIS UL387 16PR  148/145K TL</name><price>34440</price><rest>8</rest><brand>MAXXIS</brand><model>UL387</model><diameter>22.5</diameter><width>11.00</width><season>лето</season><img>https://s3.adman.com/img-zapaska/Tires/MAXXIS/UL387.jpg</img><tyretype>Грузовая</tyretype></item><item><cae>КА-00036706</cae><name>275/70R22.5    AMBERSTONE 366  148/145M 18PR TL</name><price>20716</price><rest>16</rest><brand>AMBERSTONE</brand><model>366</model><diameter>22.5</diameter><height>70</height><width>275</width><season>лето</season><img>https://s3.adman.com/img-zapaska/Tires/AMBERSTONE/366.jpg</img><tyretype>Грузовая</tyretype></item><item><cae>КА-00063772</cae><name>315/80R22.5    КАМА FORZA REG S  154/150K TL НкШЗ</name><price>24265</price><rest>2</rest><brand>Кама</brand><model>FORZA</model><diameter>22.5</diameter><height>80</height><width>315</width><season>лето</season><img>https://s3.adman.com/img-zapaska/Tires/Кама/FORZA.jpg</img><tyretype>Грузовая</tyretype></item><item><cae>КА-00037882</cae><name>315/80R22.5    BFGoodrich ROUTE CONTROL D  156/150L TL</name><price>34093</price><rest>3</rest><brand>BFGoodrich</brand><model>ROUTE CONTROL D</model><diameter>22.5</diameter><height>80</height><width>315</width><season>лето</season><img>https://s3.adman.com/img-zapaska/Tires/BFGoodrich/ROUTE_CONTROL_D.jpg</img><tyretype>Грузовая</tyretype></item><item><cae>КА-00027905</cae><name>8.25R20    КАМА NU901  133/131K TТ НкШЗ</name><price>18690</price><rest>17</rest><brand>Кама</brand><model>NU901</model><diameter>20</diameter><width>8.25</width><season>лето</season><img>https://s3.adman.com/img-zapaska/Tires/Кама/NU901.jpg</img><tyretype>Грузовая</tyretype></item><item><cae>КА-00027906</cae><name>9.00R20    КАМА NU901  144/142K TТ НкШЗ</name><price>21556</price><rest>11</rest><brand>Кама</brand><model>NU901</model><diameter>20</diameter><width>9.00</width><season>лето</season><img>https://s3.adman.com/img-zapaska/Tires/Кама/NU901.jpg</img><tyretype>Грузовая</tyretype></item><item><cae>КА-00027907</cae><name>9.00R20    КАМА NU902  144/142K TТ НкШЗ</name><price>21556</price><rest>2</rest><brand>Кама</brand><model>NU902</model><diameter>20</diameter><width>9.00</width><season>лето</season><img>https://s3.adman.com/img-zapaska/Tires/Кама/NU902.jpg</img><tyretype>Грузовая</tyretype></item><item><cae>КА-00036750</cae><name>295/80R22.5    AMBERSTONE 700  154/151K 18PR TL</name><price>24528</price><rest>28</rest><brand>AMBERSTONE</brand><model>700</model><diameter>22.5</diameter><height>80</height><width>295</width><season>лето</season><img>https://s3.adman.com/img-zapaska/Tires/AMBERSTONE/700.jpg</img><tyretype>Грузовая</tyretype></item><item><cae>00000000232</cae><name>10.00R20    КАМА-310  16PR 146/143K TT НкШЗ</name><price>19446</price><rest>9</rest><brand>Кама</brand><model>КАМА-310</model><diameter>20</diameter><width>10.00</width><season>лето</season><img>https://s3.adman.com/img-zapaska/Tires/Кама/КАМА-310.jpg</img><tyretype>Грузовая</tyretype></item><item><cae>КА-00037604</cae><name>385/65R22.5    MAXXIS UM968 20PR  160J/158 TL</name><price>39868</price><rest>24</rest><brand>MAXXIS</brand><model>UM968</model><diameter>22.5</diameter><height>65</height><width>385</width><season>лето</season><img>https://s3.adman.com/img-zapaska/Tires/MAXXIS/UM968.jpg</img><tyretype>Грузовая</tyretype></item><item><cae>КА-00036968</cae><name>12.00R20    FORZA OR A  18PR 154/150F TT НкШЗ</name><price>26407</price><rest>15</rest><brand>Кама</brand><model>FORZA OR A</model><diameter>20</diameter><width>12.00</width><season>лето</season><img>https://s3.adman.com/img-zapaska/Tires/Кама/FORZA_OR_A.jpg</img><tyretype>Грузовая</tyretype></item><item><cae>КА-00036755</cae><name>385/55R22.5    AMBERSTONE 706  160J 20PR TL</name><price>29694</price><rest>15</rest><brand>AMBERSTONE</brand><model>706</model><diameter>22.5</diameter><height>55</height><width>385</width><season>лето</season><img>https://s3.adman.com/img-zapaska/Tires/AMBERSTONE/706.jpg</img><tyretype>Грузовая</tyretype></item><item><cae>КА-00056545</cae><name>10.00R20    COMPASAL CPS60  149/146K 18PR TT</name><price>25609</price><rest>16</rest><brand>Compasal</brand><model>CPS60</model><diameter>20</diameter><width>10.00</width><season>лето</season><img>https://s3.adman.com/img-zapaska/Tires/Compasal/CPS60.jpg</img><tyretype>Грузовая</tyretype></item><item><cae>КА-00036771</cae><name>275/70R22.5    AMBERSTONE 785  148/145M 18PR TL</name><price>20716</price><rest>8</rest><brand>AMBERSTONE</brand><model>785</model><diameter>22.5</diameter><height>70</height><width>275</width><season>лето</season><img>https://s3.adman.com/img-zapaska/Tires/AMBERSTONE/785.jpg</img><tyretype>Грузовая</tyretype></item><item><cae>00000018099</cae><name>315/70R22.5    CORDIANT PROFESSIONAL FR-1 154/150L(152/148M) TL  ЯШЗ</name><price>30838</price><rest>6</rest><brand>Cordiant</brand><model>FR-1</model><diameter>22.5</diameter><height>70</height><width>315</width><season>лето</season><img>https://s3.adman.com/img-zapaska/Tires/Cordiant/FR-1.jpg</img><tyretype>Грузовая</tyretype></item><item><cae>00000023103</cae><name>315/80R22.5    КАМА NU701  156/150K TL НкШЗ</name><price>31867</price><rest>19</rest><brand>Кама</brand><model>NU701</model><diameter>22.5</diameter><height>80</height><width>315</width><season>лето</season><img>https://s3.adman.com/img-zapaska/Tires/Кама/NU701.jpg</img><tyretype>Грузовая</tyretype></item><item><cae>00000024058</cae><name>315/60R22.5    КАМА NF201+  152/148L TL НкШЗ</name><price>30565</price><rest>2</rest><brand>Кама</brand><model>NF201</model><diameter>22.5</diameter><height>60</height><width>315</width><season>лето</season><img>https://s3.adman.com/img-zapaska/Tires/Кама/NF201.jpg</img><tyretype>Грузовая</tyretype></item><item><cae>00000025921</cae><name>315/80R22.5    TYREX ALL STEEL FR-401 156/150M TL  ЯШЗ</name><price>23436</price><rest>4</rest><brand>Tyrex</brand><model>FR-401</model><diameter>22.5</diameter><height>80</height><width>315</width><season>лето</season><img>https://s3.adman.com/img-zapaska/Tires/Tyrex/FR-401.jpg</img><tyretype>Грузовая</tyretype></item><item><cae>КА-00008419</cae><name>11R22.5    КАМА NR702  148/145K TL НкШЗ</name><price>27090</price><rest>2</rest><brand>Кама</brand><model>NR702</model><diameter>22.5</diameter><width>11.00</width><season>лето</season><img>https://s3.adman.com/img-zapaska/Tires/Кама/NR702.jpg</img><tyretype>Грузовая</tyretype></item><item><cae>00000006953</cae><name>9.00R20    ИН-142Б  14PR 140/133K TT НкШЗ</name><price>17482</price><rest>4</rest><brand>Кама</brand><model>ИН-142Б</model><diameter>20</diameter><width>9.00</width><season>лето</season><img>https://s3.adman.com/img-zapaska/Tires/Кама/ИН-142Б.jpg</img><tyretype>Грузовая</tyretype></item><item><cae>КА-00036656</cae><name>7.50R16LT    AMBERSTONE 300  124/120L 16PR TT</name><price>10972</price><rest>31</rest><brand>AMBERSTONE</brand><model>300</model><diameter>16</diameter><width>7.50</width><season>лето</season><img>https://s3.adman.com/img-zapaska/Tires/AMBERSTONE/300.jpg</img><tyretype>Грузовая</tyretype></item><item><cae>КА-00057378</cae><name>315/80R22.5    THREE-A T176  20PR 156/153M TL</name><price>23908</price><rest>6</rest><brand>Three-A</brand><model>T176</model><diameter>22.5</diameter><height>80</height><width>315</width><season>лето</season><img>https://s3.adman.com/img-zapaska/Tires/Three-A/T176.jpg</img><tyretype>Грузовая</tyretype></item><item><cae>КА-00057379</cae><name>315/80R22.5    THREE-A T276+  20PR 157/154M TL</name><price>24118</price><rest>10</rest><brand>Three-A</brand><model>T276+</model><diameter>22.5</diameter><height>80</height><width>315</width><season>лето</season><img>https://s3.adman.com/img-zapaska/Tires/Three-A/T276+.jpg</img><tyretype>Грузовая</tyretype></item><item><cae>КА-00036711</cae><name>315/80R22.5    AMBERSTONE 366  157/154M 20PR TL</name><price>24213</price><rest>12</rest><brand>AMBERSTONE</brand><model>366</model><diameter>22.5</diameter><height>80</height><width>315</width><season>лето</season><img>https://s3.adman.com/img-zapaska/Tires/AMBERSTONE/366.jpg</img><tyretype>Грузовая</tyretype></item><item><cae>00000000192</cae><name>10.00R20    И-281 У-4  16PR 146/143J TT НкШЗ</name><price>20023</price><rest>8</rest><brand>Кама</brand><model>И-281</model><diameter>20</diameter><width>10.00</width><season>лето</season><img>https://s3.adman.com/img-zapaska/Tires/Кама/И-281.jpg</img><tyretype>Грузовая</tyretype></item><item><cae>00000000202</cae><name>12.00R20    ИД-304 У-4  18PR 154/149J TT НкШЗ</name><price>26638</price><rest>4</rest><brand>Кама</brand><model>ИД-304</model><diameter>20</diameter><width>12.00</width><season>лето</season><img>https://s3.adman.com/img-zapaska/Tires/Кама/ИД-304.jpg</img><tyretype>Грузовая</tyretype></item><item><cae>00000000254</cae><name>10.00R20    О-164 AUTOSTRADA  16PR 146/143K TT  ОШЗ</name><price>17325</price><rest>4</rest><brand>ОШЗ</brand><model>О-164</model><diameter>20</diameter><width>10.00</width><season>лето</season><img>https://s3.adman.com/img-zapaska/Tires/ОШЗ/О-164.jpg</img><tyretype>Грузовая</tyretype></item><item><cae>00000000257</cae><name>9.00R20    О-40БМ-1  12PR 136/133J TT  ОШЗ</name><price>15981</price><rest>26</rest><brand>ОШЗ</brand><model>О-40БМ</model><diameter>20</diameter><width>9.00</width><season>лето</season><img>https://s3.adman.com/img-zapaska/Tires/ОШЗ/О-40БМ.jpg</img><tyretype>Грузовая</tyretype></item><item><cae>00000000268</cae><name>12.00R20    О-75  18PR 154/149J TT  ОШЗ</name><price>23992</price><rest>8</rest><brand>ОШЗ</brand><model>О-75</model><diameter>20</diameter><width>12.00</width><season>лето</season><img>https://s3.adman.com/img-zapaska/Tires/ОШЗ/О-75.jpg</img><tyretype>Грузовая</tyretype></item><item><cae>00000000272</cae><name>8.25R20    TYREX CRG ROAD О-79  14PR 133/131K TT  ОШЗ</name><price>14847</price><rest>1</rest><brand>Tyrex</brand><model>О-79</model><diameter>20</diameter><width>8.25</width><season>лето</season><img>https://s3.adman.com/img-zapaska/Tires/Tyrex/О-79.jpg</img><tyretype>Грузовая</tyretype></item><item><cae>00000000277</cae><name>14.00-20    ОИ-25  14PR 147G TT  ОШЗ</name><price>38188</price><rest>6</rest><brand>ОШЗ</brand><model>ОИ-25</model><diameter>20</diameter><width>14.00</width><season>лето</season><img>https://s3.adman.com/img-zapaska/Tires/ОШЗ/ОИ-25.jpg</img><tyretype>Грузовая</tyretype></item><item><cae>00000000287</cae><name>8.25R20    У-2  10PR 125/122J TT НкШЗ</name><price>14931</price><rest>6</rest><brand>Кама</brand><model>У-2</model><diameter>20</diameter><width>8.25</width><season>лето</season><img>https://s3.adman.com/img-zapaska/Tires/Кама/У-2.jpg</img><tyretype>Грузовая</tyretype></item><item><cae>КА-00056477</cae><name>315/80R22.5    COMPASAL CPD81  156/150M 20PR TL</name><price>25441</price><rest>4</rest><brand>Compasal</brand><model>CPD81</model><diameter>22.5</diameter><height>80</height><width>315</width><season>лето</season><img>https://s3.adman.com/img-zapaska/Tires/Compasal/CPD81.jpg</img><tyretype>Грузовая</tyretype></item><item><cae>КА-00056516</cae><name>265/70R19.5    COMPASAL CPS21  143/141J 18PR TL</name><price>16296</price><rest>1</rest><brand>Compasal</brand><model>CPS21</model><diameter>19.5</diameter><height>70</height><width>265</width><season>лето</season><img>https://s3.adman.com/img-zapaska/Tires/Compasal/CPS21.jpg</img><tyretype>Грузовая</tyretype></item><item><cae>КА-00036772</cae><name>11R22.5    AMBERSTONE 785  146/143M 16PR TL</name><price>22722</price><rest>8</rest><brand>AMBERSTONE</brand><model>785</model><diameter>22.5</diameter><width>11.00</width><season>лето</season><img>https://s3.adman.com/img-zapaska/Tires/AMBERSTONE/785.jpg</img><tyretype>Грузовая</tyretype></item><item><cae>КА-00036966</cae><name>225/75R17.5    КАМА NF202  129/127M TL НкШЗ</name><price>16243</price><rest>6</rest><brand>Кама</brand><model>NF202</model><diameter>17.5</diameter><height>75</height><width>225</width><season>лето</season><img>https://s3.adman.com/img-zapaska/Tires/Кама/NF202.jpg</img><tyretype>Грузовая</tyretype></item><item><cae>КА-00038232</cae><name>385/65R22.5    КАМА FORZA REG T  160/156K TL НкШЗ</name><price>27940</price><rest>4</rest><brand>Кама</brand><model>FORZA</model><diameter>22.5</diameter><height>65</height><width>385</width><season>лето</season><img>https://s3.adman.com/img-zapaska/Tires/Кама/FORZA.jpg</img><tyretype>Грузовая</tyretype></item><item><cae>КА-00037590</cae><name>315/80R22.5    MAXXIS MA268 18PR  156/150L TL</name><price>36477</price><rest>13</rest><brand>MAXXIS</brand><model>MA268</model><diameter>22.5</diameter><height>80</height><width>315</width><season>лето</season><img>https://s3.adman.com/img-zapaska/Tires/MAXXIS/MA268.jpg</img><tyretype>Грузовая</tyretype></item><item><cae>КА-00036764</cae><name>215/75R17.5    AMBERSTONE 785  128/126M 16PR TL</name><price>11802</price><rest>13</rest><brand>AMBERSTONE</brand><model>785</model><diameter>17.5</diameter><height>75</height><width>215</width><season>лето</season><img>https://s3.adman.com/img-zapaska/Tires/AMBERSTONE/785.jpg</img><tyretype>Грузовая</tyretype></item><item><cae>00000012138</cae><name>9.00R20    ИН-142Б-1  14PR 141/138K TT  ОШЗ</name><price>16212</price><rest>4</rest><brand>ОШЗ</brand><model>ИН-142Б-1</model><diameter>20</diameter><width>9.00</width><season>лето</season><img>https://s3.adman.com/img-zapaska/Tires/ОШЗ/ИН-142Б-1.jpg</img><tyretype>Грузовая</tyretype></item><item><cae>00000025914</cae><name>385/65R22.5    CORDIANT PROFESSIONAL TR-2 160K(158L) TL  ЯШЗ</name><price>37044</price><rest>1</rest><brand>Cordiant</brand><model>TR-2</model><diameter>22.5</diameter><height>65</height><width>385</width><season>лето</season><img>https://s3.adman.com/img-zapaska/Tires/Cordiant/TR-2.jpg</img><tyretype>Грузовая</tyretype></item><item><cae>КА-00036664</cae><name>11.00R20    AMBERSTONE 300  152/149L 18PR TT</name><price>27898</price><rest>12</rest><brand>AMBERSTONE</brand><model>300</model><diameter>20</diameter><width>11.00</width><season>лето</season><img>https://s3.adman.com/img-zapaska/Tires/AMBERSTONE/300.jpg</img><tyretype>Грузовая</tyretype></item><item><cae>00000017932</cae><name>315/70R22.5    CORDIANT PROFESSIONAL DR-1 154/150L(152/148M) TL  ЯШЗ</name><price>32455</price><rest>3</rest><brand>Cordiant</brand><model>DR-1</model><diameter>22.5</diameter><height>70</height><width>315</width><season>лето</season><img>https://s3.adman.com/img-zapaska/Tires/Cordiant/DR-1.jpg</img><tyretype>Грузовая</tyretype></item><item><cae>00000015865</cae><name>245/70R19.5    CORDIANT PROFESSIONAL DR-1 136/134M TL  ЯШЗ</name><price>20517</price><rest>2</rest><brand>Cordiant</brand><model>DR-1</model><diameter>19.5</diameter><height>70</height><width>245</width><season>лето</season><img>https://s3.adman.com/img-zapaska/Tires/Cordiant/DR-1.jpg</img><tyretype>Грузовая</tyretype></item><item><cae>00000015866</cae><name>315/80R22.5    CORDIANT PROFESSIONAL DR-1  157/150L TL  ЯШЗ</name><price>35637</price><rest>4</rest><brand>Cordiant</brand><model>DR-1</model><diameter>22.5</diameter><height>80</height><width>315</width><season>лето</season><img>https://s3.adman.com/img-zapaska/Tires/Cordiant/DR-1.jpg</img><tyretype>Грузовая</tyretype></item><item><cae>КА-00056473</cae><name>275/70R22.5    COMPASAL CPD81  148/145M 16PR TL</name><price>22071</price><rest>22</rest><brand>Compasal</brand><model>CPD81</model><diameter>22.5</diameter><height>70</height><width>275</width><season>лето</season><img>https://s3.adman.com/img-zapaska/Tires/Compasal/CPD81.jpg</img><tyretype>Грузовая</tyretype></item><item><cae>00000007978</cae><name>275/70R22.5    КАМА NR201  148/145L TL НкШЗ</name><price>25084</price><rest>6</rest><brand>Кама</brand><model>NR201</model><diameter>22.5</diameter><height>70</height><width>275</width><season>лето</season><img>https://s3.adman.com/img-zapaska/Tires/Кама/NR201.jpg</img><tyretype>Грузовая</tyretype></item><item><cae>00000027329</cae><name>295/80R22.5    TYREX ALL STEEL FR-401 152/148M TL  ЯШЗ</name><price>23583</price><rest>2</rest><brand>Tyrex</brand><model>FR-401</model><diameter>22.5</diameter><height>80</height><width>295</width><season>лето</season><img>https://s3.adman.com/img-zapaska/Tires/Tyrex/FR-401.jpg</img><tyretype>Грузовая</tyretype></item><item><cae>КА-00036746</cae><name>11R22.5    AMBERSTONE 617  146/143L 16PR TL</name><price>24150</price><rest>16</rest><brand>AMBERSTONE</brand><model>617</model><diameter>22.5</diameter><width>11.00</width><season>лето</season><img>https://s3.adman.com/img-zapaska/Tires/AMBERSTONE/617.jpg</img><tyretype>Грузовая</tyretype></item><item><cae>КА-00036701</cae><name>245/70R19.5    AMBERSTONE 366  143/141J 18PR TL</name><price>15750</price><rest>15</rest><brand>AMBERSTONE</brand><model>366</model><diameter>19.5</diameter><height>70</height><width>245</width><season>лето</season><img>https://s3.adman.com/img-zapaska/Tires/AMBERSTONE/366.jpg</img><tyretype>Грузовая</tyretype></item><item><cae>КА-00036673</cae><name>8.25R16LT    AMBERSTONE 306  128/124M 16PR TT</name><price>13104</price><rest>14</rest><brand>AMBERSTONE</brand><model>306</model><diameter>16</diameter><width>8.25</width><season>лето</season><img>https://s3.adman.com/img-zapaska/Tires/AMBERSTONE/306.jpg</img><tyretype>Грузовая</tyretype></item><item><cae>00000016287</cae><name>315/80R22.5    CORDIANT PROFESSIONAL VM-1 156/150K TL  ЯШЗ</name><price>37380</price><rest>4</rest><brand>Cordiant</brand><model>VM-1</model><diameter>22.5</diameter><height>80</height><width>315</width><season>лето</season><img>https://s3.adman.com/img-zapaska/Tires/Cordiant/VM-1.jpg</img><tyretype>Грузовая</tyretype></item><item><cae>КА-00036705</cae><name>285/70R19.5    AMBERSTONE 366  150/148J 18PR TL</name><price>18322</price><rest>2</rest><brand>AMBERSTONE</brand><model>366</model><diameter>19.5</diameter><height>70</height><width>285</width><season>лето</season><img>https://s3.adman.com/img-zapaska/Tires/AMBERSTONE/366.jpg</img><tyretype>Грузовая</tyretype></item><item><cae>КА-00036698</cae><name>245/70R17.5    AMBERSTONE 366  136/134M 16PR TL</name><price>14553</price><rest>12</rest><brand>AMBERSTONE</brand><model>366</model><diameter>17.5</diameter><height>70</height><width>245</width><season>лето</season><img>https://s3.adman.com/img-zapaska/Tires/AMBERSTONE/366.jpg</img><tyretype>Грузовая</tyretype></item><item><cae>00000008964</cae><name>385/65R22.5    КАМА NT201  160K TL НкШЗ</name><price>29452</price><rest>4</rest><brand>Кама</brand><model>NT201</model><diameter>22.5</diameter><height>65</height><width>385</width><season>лето</season><img>https://s3.adman.com/img-zapaska/Tires/Кама/NT201.jpg</img><tyretype>Грузовая</tyretype></item><item><cae>КА-00023895</cae><name>11R22.5    YATAI S801  16PR 146/143M TL</name><price>20737</price><rest>1</rest><brand>Yatai</brand><model>S801</model><diameter>22.5</diameter><width>11.00</width><season>лето</season><img>https://s3.adman.com/img-zapaska/Tires/Yatai/S801.jpg</img><tyretype>Грузовая</tyretype></item><item><cae>КА-00023926</cae><name>315/80R22.5    YATAI T298  20PR 156/153K TL</name><price>26092</price><rest>2</rest><brand>Yatai</brand><model>T298</model><diameter>22.5</diameter><height>80</height><width>315</width><season>лето</season><img>https://s3.adman.com/img-zapaska/Tires/Yatai/T298.jpg</img><tyretype>Грузовая</tyretype></item><item><cae>КА-00024304</cae><name>295/80R22.5    КАМА NU701   152/148M TL НкШЗ</name><price>33243</price><rest>4</rest><brand>Кама</brand><model>NU701</model><diameter>22.5</diameter><height>80</height><width>295</width><season>лето</season><img>https://s3.adman.com/img-zapaska/Tires/Кама/NU701.jpg</img><tyretype>Грузовая</tyretype></item><item><cae>КА-00008437</cae><name>13R22.5    КАМА NR702  156/151K TL НкШЗ</name><price>34534</price><rest>6</rest><brand>Кама</brand><model>NR702</model><diameter>22.5</diameter><width>13.00</width><season>лето</season><img>https://s3.adman.com/img-zapaska/Tires/Кама/NR702.jpg</img><tyretype>Грузовая</tyretype></item><item><cae>00000022122</cae><name>235/75R17.5    CORDIANT PROFESSIONAL FR-1 132/130M TL  ЯШЗ</name><price>18564</price><rest>4</rest><brand>Cordiant</brand><model>FR-1</model><diameter>17.5</diameter><height>75</height><width>235</width><season>лето</season><img>https://s3.adman.com/img-zapaska/Tires/Cordiant/FR-1.jpg</img><tyretype>Грузовая</tyretype></item><item><cae>КА-00026746</cae><name>265/70R19.5    КАМА NU301  140/138 TL НкШЗ</name><price>20233</price><rest>4</rest><brand>Кама</brand><model>NU301</model><diameter>19.5</diameter><height>70</height><width>265</width><season>лето</season><img>https://s3.adman.com/img-zapaska/Tires/Кама/NU301.jpg</img><tyretype>Грузовая</tyretype></item><item><cae>КА-00036662</cae><name>315/80R22.5    AMBERSTONE 300  157/154M 20PR TL</name><price>24213</price><rest>9</rest><brand>AMBERSTONE</brand><model>300</model><diameter>22.5</diameter><height>80</height><width>315</width><season>лето</season><img>https://s3.adman.com/img-zapaska/Tires/AMBERSTONE/300.jpg</img><tyretype>Грузовая</tyretype></item><item><cae>КА-00037605</cae><name>11R22.5    MAXXIS MA219 16PR  148/145L TL</name><price>26943</price><rest>24</rest><brand>MAXXIS</brand><model>MA219</model><diameter>22.5</diameter><width>11.00</width><season>лето</season><img>https://s3.adman.com/img-zapaska/Tires/MAXXIS/MA219.jpg</img><tyretype>Грузовая</tyretype></item><item><cae>КА-00036880</cae><name>315/70R22.5    Fulda REGIOCONTROL 3  156/150L HL M+S 3PMSF</name><price>40792</price><rest>6</rest><brand>Fulda</brand><model>REGIOCONTROL 3</model><diameter>22.5</diameter><height>70</height><width>315</width><season>лето</season><img>https://s3.adman.com/img-zapaska/Tires/Fulda/REGIOCONTROL_3.jpg</img><tyretype>Грузовая</tyretype></item><item><cae>КА-00036693</cae><name>215/75R17.5    AMBERSTONE 366  128/126M 16PR TL</name><price>11319</price><rest>10</rest><brand>AMBERSTONE</brand><model>366</model><diameter>17.5</diameter><height>75</height><width>215</width><season>лето</season><img>https://s3.adman.com/img-zapaska/Tires/AMBERSTONE/366.jpg</img><tyretype>Грузовая</tyretype></item><item><cae>КА-00036890</cae><name>315/80R22.5    Sava ORJAK MS  156/150K M+S 3PMSF</name><price>33337</price><rest>4</rest><brand>Sava</brand><model>ORJAK MS</model><diameter>22.5</diameter><height>80</height><width>315</width><season>лето</season><img>https://s3.adman.com/img-zapaska/Tires/Sava/ORJAK_MS.jpg</img><tyretype>Грузовая</tyretype></item><item><cae>00000017735</cae><name>315/70R22.5    КАМА NF202  154/150L TL НкШЗ</name><price>25389</price><rest>4</rest><brand>Кама</brand><model>NF202</model><diameter>22.5</diameter><height>70</height><width>315</width><season>лето</season><img>https://s3.adman.com/img-zapaska/Tires/Кама/NF202.jpg</img><tyretype>Грузовая</tyretype></item><item><cae>КА-00021638</cae><name>215/75R17.5    КАМА NT202  135/133J TL НкШЗ</name><price>14374</price><rest>5</rest><brand>Кама</brand><model>NT202</model><diameter>17.5</diameter><height>75</height><width>215</width><season>лето</season><img>https://s3.adman.com/img-zapaska/Tires/Кама/NT202.jpg</img><tyretype>Грузовая</tyretype></item><item><cae>00000018658</cae><name>315/80R22.5    КАМА NF201  156/150L TL НкШЗ</name><price>26544</price><rest>2</rest><brand>Кама</brand><model>NF201</model><diameter>22.5</diameter><height>80</height><width>315</width><season>лето</season><img>https://s3.adman.com/img-zapaska/Tires/Кама/NF201.jpg</img><tyretype>Грузовая</tyretype></item><item><cae>КА-00055161</cae><name>315/80R22.5    КАМА NF202  156/150L TL НкШЗ</name><price>26260</price><rest>3</rest><brand>Кама</brand><model>NF202</model><diameter>22.5</diameter><height>80</height><width>315</width><season>лето</season><img>https://s3.adman.com/img-zapaska/Tires/Кама/NF202.jpg</img><tyretype>Грузовая</tyretype></item><item><cae>КА-00056626</cae><name>295/75R22.5    COMPASAL CPD88  148/145L 18PR TL</name><price>22753</price><rest>7</rest><brand>Compasal</brand><model>CPD88</model><diameter>22.5</diameter><height>75</height><width>295</width><season>лето</season><img>https://s3.adman.com/img-zapaska/Tires/Compasal/CPD88.jpg</img><tyretype>Грузовая</tyretype></item><item><cae>00000000205</cae><name>500/70-20 (1200x500-508)    ИД-П284  16PR 156F TT  ОШЗ</name><price>43428</price><rest>7</rest><brand>ОШЗ</brand><model>ИД-П284</model><diameter>20</diameter><height>70</height><width>500</width><season>лето</season><img>https://s3.adman.com/img-zapaska/Tires/ОШЗ/ИД-П284.jpg</img><tyretype>Грузовая</tyretype></item><item><cae>00000003678</cae><name>12.00R20    КАМА-310  18PR 154/149J TT НкШЗ</name><price>24213</price><rest>3</rest><brand>Кама</brand><model>КАМА-310</model><diameter>20</diameter><width>12.00</width><season>лето</season><img>https://s3.adman.com/img-zapaska/Tires/Кама/КАМА-310.jpg</img><tyretype>Грузовая</tyretype></item><item><cae>КА-00020098</cae><name>11R22.5    КАМА NF702  148/145K TL НкШЗ</name><price>26208</price><rest>8</rest><brand>Кама</brand><model>NF702</model><diameter>22.5</diameter><width>11.00</width><season>лето</season><img>https://s3.adman.com/img-zapaska/Tires/Кама/NF702.jpg</img><tyretype>Грузовая</tyretype></item><item><cae>КА-00036751</cae><name>315/80R22.5    AMBERSTONE 700  157/154K 20PR TL</name><price>24759</price><rest>33</rest><brand>AMBERSTONE</brand><model>700</model><diameter>22.5</diameter><height>80</height><width>315</width><season>лето</season><img>https://s3.adman.com/img-zapaska/Tires/AMBERSTONE/700.jpg</img><tyretype>Грузовая</tyretype></item><item><cae>КА-00036889</cae><name>315/80R22.5    Sava AVANT MS2  156/150K M+S</name><price>30954</price><rest>6</rest><brand>Sava</brand><model>AVANT MS2</model><diameter>22.5</diameter><height>80</height><width>315</width><season>лето</season><img>https://s3.adman.com/img-zapaska/Tires/Sava/AVANT_MS2.jpg</img><tyretype>Грузовая</tyretype></item><item><cae>КА-00036655</cae><name>7.00R16LT    AMBERSTONE 300  118/114L 14PR TT</name><price>9849</price><rest>3</rest><brand>AMBERSTONE</brand><model>300</model><diameter>16</diameter><width>7.00</width><season>лето</season><img>https://s3.adman.com/img-zapaska/Tires/AMBERSTONE/300.jpg</img><tyretype>Грузовая</tyretype></item><item><cae>КА-00036874</cae><name>315/80R22.5    Goodyear OMNITRAC S HD  156/150K M+S 3PMSF</name><price>35721</price><rest>3</rest><brand>Goodyear</brand><model>OMNITRAC S HD</model><diameter>22.5</diameter><height>80</height><width>315</width><season>лето</season><img>https://s3.adman.com/img-zapaska/Tires/Goodyear/OMNITRAC_S_HD.jpg</img><tyretype>Грузовая</tyretype></item><item><cae>КА-00056471</cae><name>245/70R19.5    COMPASAL CPD81  143/141J 18PR TL</name><price>15592</price><rest>1</rest><brand>Compasal</brand><model>CPD81</model><diameter>19.5</diameter><height>70</height><width>245</width><season>лето</season><img>https://s3.adman.com/img-zapaska/Tires/Compasal/CPD81.jpg</img><tyretype>Грузовая</tyretype></item><item><cae>00000023539</cae><name>265/70R19.5    КАМА NT202  143/141J TL НкШЗ</name><price>21367</price><rest>1</rest><brand>Кама</brand><model>NT202</model><diameter>19.5</diameter><height>70</height><width>265</width><season>лето</season><img>https://s3.adman.com/img-zapaska/Tires/Кама/NT202.jpg</img><tyretype>Грузовая</tyretype></item><item><cae>00000023540</cae><name>285/70R19.5    КАМА NF202  145/143M TL НкШЗ</name><price>22060</price><rest>6</rest><brand>Кама</brand><model>NF202</model><diameter>19.5</diameter><height>70</height><width>285</width><season>лето</season><img>https://s3.adman.com/img-zapaska/Tires/Кама/NF202.jpg</img><tyretype>Грузовая</tyretype></item><item><cae>00000023775</cae><name>265/70R19.5    КАМА NR202  140/138M TL НкШЗ</name><price>20569</price><rest>4</rest><brand>Кама</brand><model>NR202</model><diameter>19.5</diameter><height>70</height><width>265</width><season>лето</season><img>https://s3.adman.com/img-zapaska/Tires/Кама/NR202.jpg</img><tyretype>Грузовая</tyretype></item><item><cae>КА-00056547</cae><name>11.00R20    COMPASAL CPS60  152/149K 18PR TT</name><price>27027</price><rest>22</rest><brand>Compasal</brand><model>CPS60</model><diameter>20</diameter><width>11.00</width><season>лето</season><img>https://s3.adman.com/img-zapaska/Tires/Compasal/CPS60.jpg</img><tyretype>Грузовая</tyretype></item><item><cae>КА-00036882</cae><name>315/80R22.5    Fulda REGIOFORCE 3  156L/154M M+S 3PMSF</name><price>34923</price><rest>4</rest><brand>Fulda</brand><model>REGIOFORCE 3</model><diameter>22.5</diameter><height>80</height><width>315</width><season>лето</season><img>https://s3.adman.com/img-zapaska/Tires/Fulda/REGIOFORCE_3.jpg</img><tyretype>Грузовая</tyretype></item><item><cae>00000028384</cae><name>295/80R22.5    КАМА NF202   152/148M TL НкШЗ</name><price>24349</price><rest>12</rest><brand>Кама</brand><model>NF202</model><diameter>22.5</diameter><height>80</height><width>295</width><season>лето</season><img>https://s3.adman.com/img-zapaska/Tires/Кама/NF202.jpg</img><tyretype>Грузовая</tyretype></item><item><cae>КА-00023927</cae><name>385/65R22.5    YATAI T186  20PR 160K TL</name><price>27510</price><rest>&gt;40</rest><brand>Yatai</brand><model>T186</model><diameter>22.5</diameter><height>65</height><width>385</width><season>лето</season><img>https://s3.adman.com/img-zapaska/Tires/Yatai/T186.jpg</img><tyretype>Грузовая</tyretype></item><item><cae>КА-00050932</cae><name>275/70R22.5    КАМА NF202  148/145M TL НкШЗ</name><price>23593</price><rest>6</rest><brand>Кама</brand><model>NF202</model><diameter>22.5</diameter><height>70</height><width>275</width><season>лето</season><img>https://s3.adman.com/img-zapaska/Tires/Кама/NF202.jpg</img><tyretype>Грузовая</tyretype></item><item><cae>КА-00036658</cae><name>8.25R20    AMBERSTONE 300  139/137L 16PR TT</name><price>17293</price><rest>19</rest><brand>AMBERSTONE</brand><model>300</model><diameter>20</diameter><width>8.25</width><season>лето</season><img>https://s3.adman.com/img-zapaska/Tires/AMBERSTONE/300.jpg</img><tyretype>Грузовая</tyretype></item><item><cae>00000000195</cae><name>11.00R20    И-68А  16PR 150/146K TT НкШЗ</name><price>22281</price><rest>4</rest><brand>Кама</brand><model>И-68А</model><diameter>20</diameter><width>11.00</width><season>лето</season><img>https://s3.adman.com/img-zapaska/Tires/Кама/И-68А.jpg</img><tyretype>Грузовая</tyretype></item><item><cae>00000000206</cae><name>8.25-20    ИК-6АМО  10PR 125/122E TT  ОШЗ</name><price>13146</price><rest>8</rest><brand>ОШЗ</brand><model>ИК-6АМО</model><diameter>20</diameter><width>8.25</width><season>лето</season><img>https://s3.adman.com/img-zapaska/Tires/ОШЗ/ИК-6АМО.jpg</img><tyretype>Грузовая</tyretype></item><item><cae>00000000233</cae><name>11.00R20    КАМА-310  16PR 150/146K TT НкШЗ</name><price>19887</price><rest>4</rest><brand>Кама</brand><model>КАМА-310</model><diameter>20</diameter><width>11.00</width><season>лето</season><img>https://s3.adman.com/img-zapaska/Tires/Кама/КАМА-310.jpg</img><tyretype>Грузовая</tyretype></item><item><cae>00000000256</cae><name>11.00R20    TYREX CRG UNIVERSAL О-168  16PR 150/146K TT  ОШЗ</name><price>19477</price><rest>3</rest><brand>Tyrex</brand><model>О-168</model><diameter>20</diameter><width>11.00</width><season>лето</season><img>https://s3.adman.com/img-zapaska/Tires/Tyrex/О-168.jpg</img><tyretype>Грузовая</tyretype></item><item><cae>00000000271</cae><name>8.25R20    TYREX CRG ROAD О-79  12PR 130/128K TT  ОШЗ</name><price>13755</price><rest>9</rest><brand>Tyrex</brand><model>О-79</model><diameter>20</diameter><width>8.25</width><season>лето</season><img>https://s3.adman.com/img-zapaska/Tires/Tyrex/О-79.jpg</img><tyretype>Грузовая</tyretype></item><item><cae>КА-00035918</cae><name>315/80R22.5    КАМА FORZA Mix A  156/150K TL НкШЗ</name><price>25473</price><rest>4</rest><brand>Кама</brand><model>FORZA</model><diameter>22.5</diameter><height>80</height><width>315</width><season>лето</season><img>https://s3.adman.com/img-zapaska/Tires/Кама/FORZA.jpg</img><tyretype>Грузовая</tyretype></item><item><cae>КА-00063769</cae><name>295/80R22.5    КАМА FORZA REG D   152/148K TL НкШЗ</name><price>24423</price><rest>4</rest><brand>Кама</brand><model>REG D</model><diameter>22.5</diameter><height>80</height><width>295</width><season>лето</season><img>https://s3.adman.com/img-zapaska/Tires/Кама/REG_D.jpg</img><tyretype>Грузовая</tyretype></item><item><cae>КА-00036744</cae><name>295/75R22.5    AMBERSTONE 600  146/143L 16PR TL</name><price>22228</price><rest>10</rest><brand>AMBERSTONE</brand><model>600</model><diameter>22.5</diameter><height>75</height><width>295</width><season>лето</season><img>https://s3.adman.com/img-zapaska/Tires/AMBERSTONE/600.jpg</img><tyretype>Грузовая</tyretype></item><item><cae>00000009248</cae><name>295/80R22.5    КАМА NR202  152/148M TL НкШЗ</name><price>25788</price><rest>3</rest><brand>Кама</brand><model>NR202</model><diameter>22.5</diameter><height>80</height><width>295</width><season>лето</season><img>https://s3.adman.com/img-zapaska/Tires/Кама/NR202.jpg</img><tyretype>Грузовая</tyretype></item><item><cae>00000000203</cae><name>12.00R20    ИД-304 У-4  18PR 154/149J TT  ОШЗ</name><price>24171</price><rest>3</rest><brand>ОШЗ</brand><model>ИД-304</model><diameter>20</diameter><width>12.00</width><season>лето</season><img>https://s3.adman.com/img-zapaska/Tires/ОШЗ/ИД-304.jpg</img><tyretype>Грузовая</tyretype></item><item><cae>00000000210</cae><name>9.00R20    ИН-142Б-1  12PR 136/133J TT  ОШЗ</name><price>15897</price><rest>8</rest><brand>ОШЗ</brand><model>ИН-142Б-1</model><diameter>20</diameter><width>9.00</width><season>лето</season><img>https://s3.adman.com/img-zapaska/Tires/ОШЗ/ИН-142Б-1.jpg</img><tyretype>Грузовая</tyretype></item><item><cae>КА-00036105</cae><name>315/80R22.5    КАМА NU704  156/150L TL НкШЗ</name><price>33463</price><rest>8</rest><brand>Кама</brand><model>NU704</model><diameter>22.5</diameter><height>80</height><width>315</width><season>лето</season><img>https://s3.adman.com/img-zapaska/Tires/Кама/NU704.jpg</img><tyretype>Грузовая</tyretype></item><item><cae>КА-00036512</cae><name>215/75R17.5    CORDIANT PROFESSIONAL TR-1 135/133J TL ЯШЗ</name><price>15088</price><rest>5</rest><brand>Cordiant</brand><model>TR-1</model><diameter>17.5</diameter><height>75</height><width>215</width><season>лето</season><img>https://s3.adman.com/img-zapaska/Tires/Cordiant/TR-1.jpg</img><tyretype>Грузовая</tyretype></item><item><cae>КА-00036756</cae><name>295/80R22.5    AMBERSTONE 755  154/151M 18PR TL</name><price>24528</price><rest>24</rest><brand>AMBERSTONE</brand><model>755</model><diameter>22.5</diameter><height>80</height><width>295</width><season>лето</season><img>https://s3.adman.com/img-zapaska/Tires/AMBERSTONE/755.jpg</img><tyretype>Грузовая</tyretype></item><item><cae>КА-00041757</cae><name>245/70R17.5    КАМА NF202  136/134M TL НкШЗ</name><price>16359</price><rest>2</rest><brand>Кама</brand><model>NF202</model><diameter>17.5</diameter><height>70</height><width>245</width><season>лето</season><img>https://s3.adman.com/img-zapaska/Tires/Кама/NF202.jpg</img><tyretype>Грузовая</tyretype></item><item><cae>00000004137</cae><name>12.00R20    КАМА-701  18PR 154/150F TT НкШЗ</name><price>27205</price><rest>6</rest><brand>Кама</brand><model>КАМА-701</model><diameter>20</diameter><width>12.00</width><season>лето</season><img>https://s3.adman.com/img-zapaska/Tires/Кама/КАМА-701.jpg</img><tyretype>Грузовая</tyretype></item><item><cae>КА-00056475</cae><name>295/80R22.5    COMPASAL CPD81  154/151M 18PR TL</name><price>23488</price><rest>8</rest><brand>Compasal</brand><model>CPD81</model><diameter>22.5</diameter><height>80</height><width>295</width><season>лето</season><img>https://s3.adman.com/img-zapaska/Tires/Compasal/CPD81.jpg</img><tyretype>Грузовая</tyretype></item><item><cae>00000025801</cae><name>11.00R20    TYREX CRG VM-310  16PR 150/146K TT  ОШЗ</name><price>20895</price><rest>4</rest><brand>Tyrex</brand><model>VM-310</model><diameter>20</diameter><width>11.00</width><season>лето</season><img>https://s3.adman.com/img-zapaska/Tires/Tyrex/VM-310.jpg</img><tyretype>Грузовая</tyretype></item><item><cae>00000016917</cae><name>235/75R17.5    КАМА NT202  143/141J TL НкШЗ</name><price>15372</price><rest>8</rest><brand>Кама</brand><model>NT202</model><diameter>17.5</diameter><height>75</height><width>235</width><season>лето</season><img>https://s3.adman.com/img-zapaska/Tires/Кама/NT202.jpg</img><tyretype>Грузовая</tyretype></item><item><cae>КА-00037883</cae><name>315/80R22.5    BFGoodrich CROSS CONTROL S2  156/150K TL</name><price>33579</price><rest>2</rest><brand>BFGoodrich</brand><model>CROSS CONTROL S2</model><diameter>22.5</diameter><height>80</height><width>315</width><season>лето</season><img>https://s3.adman.com/img-zapaska/Tires/BFGoodrich/CROSS_CONTROL_S2.jpg</img><tyretype>Грузовая</tyretype></item></items>